odoo8_addon_hr_timesheet_improvement-8.0.0.1.0-py2.7-nspkg.pth
odoo_addons/hr_timesheet_improvement/hr_timesheet_view.xml
odoo_addons/hr_timesheet_improvement/__openerp__.py
odoo_addons/hr_timesheet_improvement/hr_attendance.py
odoo_addons/hr_timesheet_improvement/__init__.py
odoo_addons/hr_timesheet_improvement/hr_timesheet.py
odoo_addons/hr_timesheet_improvement/README.rst
odoo_addons/hr_timesheet_improvement/tests/test_timesheet_improvement.py
odoo_addons/hr_timesheet_improvement/tests/__init__.py
odoo_addons/hr_timesheet_improvement/static/description/icon.png
odoo8_addon_hr_timesheet_improvement-8.0.0.1.0.dist-info/top_level.txt
odoo8_addon_hr_timesheet_improvement-8.0.0.1.0.dist-info/WHEEL
odoo8_addon_hr_timesheet_improvement-8.0.0.1.0.dist-info/RECORD
odoo8_addon_hr_timesheet_improvement-8.0.0.1.0.dist-info/metadata.json
odoo8_addon_hr_timesheet_improvement-8.0.0.1.0.dist-info/DESCRIPTION.rst
odoo8_addon_hr_timesheet_improvement-8.0.0.1.0.dist-info/METADATA
odoo8_addon_hr_timesheet_improvement-8.0.0.1.0.dist-info/namespace_packages.txt
